{"cameraMode":{"drawMode":0,"name":"Shaded","section":"Shading Mode"},"sceneLighting":true,"audioPlay":false,"sceneViewState":{"showFog":true,"showMaterialUpdate":false,"showSkybox":true,"showFlares":true,"showImageEffects":true,"showParticleSystems":true},"in2DMode":false,"pivot":{"x":2.7037038803100588,"y":-0.6220602989196777,"z":-3.5231711864471437},"rotation":{"x":-0.021476740017533304,"y":0.9630603194236755,"z":-0.2559984624385834,"w":-0.08079668879508972},"size":3.9862897396087648,"orthographic":false}